echodataflow/__init__.py
echodataflow/echodataflow_cli.py
echodataflow/version.py
echodataflow/aspects/__init__.py
echodataflow/aspects/echodataflow_aspect.py
echodataflow/aspects/singleton_echodataflow.py
echodataflow/config/__init__.py
echodataflow/config/datastore.yaml
echodataflow/config/logging_config.yaml
echodataflow/config/pipeline.yaml
echodataflow/models/__init__.py
echodataflow/models/datastore.py
echodataflow/models/db_log_model.py
echodataflow/models/echodataflow_config.py
echodataflow/models/output_model.py
echodataflow/models/pipeline.py
echodataflow/rule_engine/__init__.py
echodataflow/rule_engine/dependency_engine.py
echodataflow/rule_engine/echodataflow_rules.txt
echodataflow/stages/__init__.py
echodataflow/stages/docker_trigger.py
echodataflow/stages/echodataflow.py
echodataflow/stages/echodataflow_trigger.py
echodataflow/stages/subflows/__init__.py
echodataflow/stages/subflows/add_depth.py
echodataflow/stages/subflows/add_location.py
echodataflow/stages/subflows/apply_mask.py
echodataflow/stages/subflows/combine_echodata.py
echodataflow/stages/subflows/compute_MVBS.py
echodataflow/stages/subflows/compute_SV.py
echodataflow/stages/subflows/compute_TS.py
echodataflow/stages/subflows/frequency_differencing.py
echodataflow/stages/subflows/initialization_flow.py
echodataflow/stages/subflows/open_raw.py
echodataflow/tests/__init__.py
echodataflow/tests/AWS/AWSEchoflowDemo.ipynb
echodataflow/tests/AWS/datastore.yaml
echodataflow/tests/AWS/pipeline.yaml
echodataflow/tests/offline/LocalEchoflowDemo.ipynb
echodataflow/tests/offline/datastore.yaml
echodataflow/tests/offline/pipeline.yaml
echodataflow/utils/__init__.py
echodataflow/utils/config_utils.py
echodataflow/utils/databse_utils.py
echodataflow/utils/file_utils.py
echodataflow/utils/function_utils.py
echodataflow/utils/log_util.py
echodataflow/utils/rest_utils.py
echodataflow-0.1.4.dist-info/LICENSE
echodataflow-0.1.4.dist-info/METADATA
echodataflow-0.1.4.dist-info/WHEEL
echodataflow-0.1.4.dist-info/entry_points.txt
echodataflow-0.1.4.dist-info/top_level.txt
echodataflow-0.1.4.dist-info/RECORD
