Metadata-Version: 2.1
Name: echodataflow
Version: 0.1.4
Summary: Sonar conversion pipeline tool with echopype
Home-page: https://github.com/OSOceanAcoustics/echodataflow
Author: Soham Butala and Landung Setiawan
Author-email: sohambutala7@gmail.com | landungs@uw.edu
Maintainer: Soham Butala
Maintainer-email: sohambutala7@gmail.com
License: MIT
Platform: OS Independent
Classifier: Development Status :: 3 - Alpha
Classifier: Intended Audience :: Developers
Classifier: Topic :: Software Development :: Build Tools
Classifier: License :: OSI Approved :: MIT License
Classifier: Operating System :: OS Independent
Classifier: Programming Language :: Python :: 3.9
Classifier: Programming Language :: Python :: 3.10
Classifier: Topic :: Software Development :: Libraries :: Python Modules
Classifier: Topic :: Scientific/Engineering
Requires-Python: <3.11,>=3.8
License-File: LICENSE
Requires-Dist: requests
Requires-Dist: prefect >=2
Requires-Dist: echopype >=0.6.3
Requires-Dist: jinja2
Requires-Dist: prefect-dask
Requires-Dist: pydantic
Requires-Dist: prefect-aws
Requires-Dist: prefect-azure
Requires-Dist: jupyter
Requires-Dist: jupyter-book
Requires-Dist: fastapi
Requires-Dist: sphinx
Requires-Dist: kafka-python
Provides-Extra: all
Requires-Dist: pytest ; extra == 'all'
Requires-Dist: pytest-cov ; extra == 'all'
Requires-Dist: pytest-flake8 ; extra == 'all'
Requires-Dist: pytest-xdist ; extra == 'all'
Requires-Dist: pytest-mock ; extra == 'all'
Requires-Dist: black ; extra == 'all'
Requires-Dist: check-manifest ; extra == 'all'
Requires-Dist: flake8 ; extra == 'all'
Requires-Dist: flake8-builtins ; extra == 'all'
Requires-Dist: flake8-comprehensions ; extra == 'all'
Requires-Dist: flake8-mutable ; extra == 'all'
Requires-Dist: flake8-print ; extra == 'all'
Requires-Dist: isort ; extra == 'all'
Requires-Dist: mypy ; extra == 'all'
Requires-Dist: numpydoc ; extra == 'all'
Requires-Dist: pre-commit ; extra == 'all'
Requires-Dist: pylint ; extra == 'all'
Requires-Dist: sphinx ; extra == 'all'
Requires-Dist: sphinx-automodapi ; extra == 'all'
Provides-Extra: docs
Requires-Dist: sphinx ; extra == 'docs'
Requires-Dist: sphinx-automodapi ; extra == 'docs'
Provides-Extra: lint
Requires-Dist: black ; extra == 'lint'
Requires-Dist: check-manifest ; extra == 'lint'
Requires-Dist: flake8 ; extra == 'lint'
Requires-Dist: flake8-builtins ; extra == 'lint'
Requires-Dist: flake8-comprehensions ; extra == 'lint'
Requires-Dist: flake8-mutable ; extra == 'lint'
Requires-Dist: flake8-print ; extra == 'lint'
Requires-Dist: isort ; extra == 'lint'
Requires-Dist: mypy ; extra == 'lint'
Requires-Dist: numpydoc ; extra == 'lint'
Requires-Dist: pre-commit ; extra == 'lint'
Requires-Dist: pylint ; extra == 'lint'
Provides-Extra: test
Requires-Dist: pytest ; extra == 'test'
Requires-Dist: pytest-cov ; extra == 'test'
Requires-Dist: pytest-flake8 ; extra == 'test'
Requires-Dist: pytest-xdist ; extra == 'test'
Requires-Dist: pytest-mock ; extra == 'test'
